hyperflask/__init__.py
hyperflask/__main__.py
hyperflask/actors.py
hyperflask/app.py
hyperflask/cli/__init__.py
hyperflask/cli/reloader.py
hyperflask/cli/runner.py
hyperflask/cli/scaffold.py
hyperflask/cli/worker.py
hyperflask/components/__init__.py
hyperflask/components/alpine.py
hyperflask/components/core.py
hyperflask/components/jsx.py
hyperflask/components/webcomponent.py
hyperflask/factory.py
hyperflask/forms/__init__.py
hyperflask/forms/fields.py
hyperflask/forms/widgets.py
hyperflask/layouts/email.mjml
hyperflask/layouts/web.html
hyperflask/model.py
hyperflask/page_helpers.py
hyperflask/security.py
hyperflask/static/alpine-csp.js
hyperflask/static/alpine.js
hyperflask/static/app.css
hyperflask/static/app.js
hyperflask/static/htmx-exts.js
hyperflask/static/react.js
hyperflask/static/stimulus.js
hyperflask/static/translations.js
hyperflask/ui/daisyui/Accordion.html
hyperflask/ui/daisyui/AccordionPanel.html
hyperflask/ui/daisyui/Alert.html
hyperflask/ui/daisyui/Avatar.html
hyperflask/ui/daisyui/AvatarGroup.html
hyperflask/ui/daisyui/Badge.html
hyperflask/ui/daisyui/Breadcrumbs.html
hyperflask/ui/daisyui/BreadcrumbsItem.html
hyperflask/ui/daisyui/Button.html
hyperflask/ui/daisyui/Card.html
hyperflask/ui/daisyui/CardActions.html
hyperflask/ui/daisyui/CardTitle.html
hyperflask/ui/daisyui/ChatBubble.html
hyperflask/ui/daisyui/Checkbox.html
hyperflask/ui/daisyui/CollapsibleSubMenu.html
hyperflask/ui/daisyui/Countdown.html
hyperflask/ui/daisyui/Divider.html
hyperflask/ui/daisyui/Drawer.html
hyperflask/ui/daisyui/DrawerContent.html
hyperflask/ui/daisyui/DrawerSide.html
hyperflask/ui/daisyui/Dropdown.html
hyperflask/ui/daisyui/DropdownItem.html
hyperflask/ui/daisyui/Fieldset.html
hyperflask/ui/daisyui/FieldsetLegend.html
hyperflask/ui/daisyui/FileInput.html
hyperflask/ui/daisyui/Filter.html
hyperflask/ui/daisyui/FilterItem.html
hyperflask/ui/daisyui/Footer.html
hyperflask/ui/daisyui/FooterLink.html
hyperflask/ui/daisyui/FooterNav.html
hyperflask-0.5.2.dist-info/WHEEL
hyperflask-0.5.2.dist-info/entry_points.txt
hyperflask-0.5.2.dist-info/METADATA
hyperflask-0.5.2.dist-info/RECORD
