Metadata-Version: 2.4
Name: hyperflask
Version: 0.5.2
Summary: Full stack web framework
Author: Maxime Bouroumeau-Fuseau
Author-email: Maxime Bouroumeau-Fuseau <maxime.bouroumeau@gmail.com>
License-Expression: MIT
Requires-Dist: flask>=3.0.0,<4.0.0
Requires-Dist: flask-assets-pipeline~=0.8
Requires-Dist: flask-babel-hyper~=5.1
Requires-Dist: flask-collections~=0.3
Requires-Dist: flask-configurator~=0.1
Requires-Dist: flask-debugtoolbar~=0.16
Requires-Dist: flask-file-routes~=0.3
Requires-Dist: flask-files~=0.2
Requires-Dist: flask-geo~=0.1
Requires-Dist: flask-mailman-templates~=0.1
Requires-Dist: flask-mercure-sse~=0.4
Requires-Dist: flask-sqlorm~=0.3
Requires-Dist: flask-super-macros~=0.2
Requires-Dist: flask-suspense~=0.3
Requires-Dist: flask-wtf~=1.2
Requires-Dist: frozen-flask~=1.0
Requires-Dist: dramatiq>=1.18.0
Requires-Dist: dramatiq-sqlite~=0.1
Requires-Dist: gunicorn~=23.0
Requires-Dist: honcho~=2.0
Requires-Dist: html-sanitizer~=2.6
Requires-Dist: htmx-flask~=0.1
Requires-Dist: jinja-layout~=0.5
Requires-Dist: jinja-wtforms~=0.2
Requires-Dist: periodiq~=0.13
Requires-Dist: python-slugify~=8.0.4
Requires-Dist: watchdog>=6.0.0
Requires-Dist: pillow>=11.3.0
Requires-Python: >=3.10
Project-URL: Repository, https://github.com/hyperflask/hyperflask
